bccovideda/__init__.py
bccovideda/get_data.py
bccovideda/plot_hist_by_cond.py
bccovideda/plot_line_by_date.py
bccovideda/show_summary_stat.py
bccovideda-1.1.0.dist-info/LICENSE
bccovideda-1.1.0.dist-info/WHEEL
bccovideda-1.1.0.dist-info/METADATA
bccovideda-1.1.0.dist-info/RECORD
