Metadata-Version: 2.1
Name: bccovideda
Version: 1.1.0
Summary: A package to download BC covid data and create simple EDA
Home-page: https://github.com/UBC-MDS/bccovideda
License: MIT
Author: MDS 2021 DSCI 524 Group 25
Requires-Python: >=3.9,<4.0
Classifier: License :: OSI Approved :: MIT License
Classifier: Programming Language :: Python :: 3
Classifier: Programming Language :: Python :: 3.10
Classifier: Programming Language :: Python :: 3.9
Requires-Dist: altair (>=4.2.0,<5.0.0)
Requires-Dist: altair-saver (>=0.5.0,<0.6.0)
Requires-Dist: ipykernel (>=6.7.0,<7.0.0)
Requires-Dist: pandas (>=1.3.5,<2.0.0)
Requires-Dist: requests (>=2.27.1,<3.0.0)
Project-URL: Documentation, https://bccovideda.readthedocs.io
Project-URL: Repository, https://github.com/UBC-MDS/bccovideda
